kaa_sdk/__init__.py
kaa_sdk/common.py
kaa_sdk/config.py
kaa_sdk/exceptions.py
kaa_sdk/file_utils.py
kaa_sdk/token.py
kaa_sdk/epts/__init__.py
kaa_sdk/epts/v1/__init__.py
kaa_sdk/epts/v1/api.py
kaa_sdk/rci/__init__.py
kaa_sdk/rci/v1/__init__.py
kaa_sdk/rci/v1/api.py
kaa_sdk-0.1.8.dist-info/METADATA
kaa_sdk-0.1.8.dist-info/WHEEL
kaa_sdk-0.1.8.dist-info/top_level.txt
kaa_sdk-0.1.8.dist-info/RECORD
