Metadata-Version: 2.1
Name: kaa-sdk
Version: 0.1.8
Summary: Python client for Kaa API
Home-page: UNKNOWN
Author: Alexandr Agitolyev
Author-email: aagitolyev@kaaiot.io
License: UNKNOWN
Platform: UNKNOWN
Requires-Dist: requests
